xinhou_openai_framework/__init__.py
xinhou_openai_framework/core/__init__.py
xinhou_openai_framework/core/annotations/BeanAnnotations.py
xinhou_openai_framework/core/annotations/__init__.py
xinhou_openai_framework/core/beans/BeanFactory.py
xinhou_openai_framework/core/beans/BeansContext.py
xinhou_openai_framework/core/beans/__init__.py
xinhou_openai_framework/core/cache/CacheHandler.py
xinhou_openai_framework/core/cache/CacheManager.py
xinhou_openai_framework/core/cache/RedisConnectionPool.py
xinhou_openai_framework/core/cache/__init__.py
xinhou_openai_framework/core/common/__init__.py
xinhou_openai_framework/core/common/controller/CommonController.py
xinhou_openai_framework/core/common/controller/GenerateCodeController.py
xinhou_openai_framework/core/common/controller/__init__.py
xinhou_openai_framework/core/common/func/__init__.py
xinhou_openai_framework/core/common/schema/GenerateCodeSchema.py
xinhou_openai_framework/core/common/schema/GenerateProjectSchema.py
xinhou_openai_framework/core/common/schema/__init__.py
xinhou_openai_framework/core/common/service/__init__.py
xinhou_openai_framework/core/config/ConfigHandler.py
xinhou_openai_framework/core/config/__init__.py
xinhou_openai_framework/core/contents/AppContents.py
xinhou_openai_framework/core/contents/__init__.py
xinhou_openai_framework/core/context/ContextHandler.py
xinhou_openai_framework/core/context/__init__.py
xinhou_openai_framework/core/context/model/AppContext.py
xinhou_openai_framework/core/context/model/ApplicationConfig.py
xinhou_openai_framework/core/context/model/FrameworkConfig.py
xinhou_openai_framework/core/context/model/NacosConfig.py
xinhou_openai_framework/core/context/model/SystemContext.py
xinhou_openai_framework/core/context/model/__init__.py
xinhou_openai_framework/core/db/DatabaseHandler.py
xinhou_openai_framework/core/db/DatabaseManager.py
xinhou_openai_framework/core/db/__init__.py
xinhou_openai_framework/core/decorator/BaseDecorator.py
xinhou_openai_framework-20250408001.dist-info/METADATA
xinhou_openai_framework-20250408001.dist-info/WHEEL
xinhou_openai_framework-20250408001.dist-info/top_level.txt
xinhou_openai_framework-20250408001.dist-info/RECORD
