Metadata-Version: 2.1
Name: xinhou-openai-framework
Version: 20250408001
Summary: XINHOU-OPENAI-FRAMEWORK基础框架，主要提供应用服务的底层支持技术代码支撑，通过该框架可以快速实现单服务、微服务、消息队列、ORM的快速开发！
Home-page: http://gitlab.xinhouai.com/openai/xinhou-openai-framework.git
Author: shenpeng
Author-email: sp_hrz@qq.com
Classifier: Development Status :: 5 - Production/Stable
Classifier: Intended Audience :: Developers
Classifier: License :: Other/Proprietary License
Classifier: Programming Language :: Python :: 3
Classifier: Operating System :: MacOS
Classifier: Topic :: Software Development :: Libraries :: Python Modules
Requires-Python: >=3.9
Requires-Dist: aiohttp ==3.9.3
Requires-Dist: aioredis ==1.3.1
Requires-Dist: aiosignal ==1.3.1
Requires-Dist: aliyun-python-sdk-core ==2.14.0
Requires-Dist: aliyun-python-sdk-kms ==2.16.2
Requires-Dist: annotated-types ==0.6.0
Requires-Dist: anyio ==3.7.1
Requires-Dist: APScheduler ==3.10.4
Requires-Dist: async-timeout ==4.0.3
Requires-Dist: attrs ==23.2.0
Requires-Dist: cffi ==1.16.0
Requires-Dist: charset-normalizer ==3.3.2
Requires-Dist: click ==8.1.7
Requires-Dist: colorlog ==6.8.2
Requires-Dist: crcmod ==1.7
Requires-Dist: cryptography ==42.0.2
Requires-Dist: decorator ==4.4.2
Requires-Dist: docutils ==0.20.1
Requires-Dist: docx ==0.2.4
Requires-Dist: et-xmlfile ==1.1.0
Requires-Dist: exceptiongroup ==1.2.0
Requires-Dist: fastapi ==0.110.3
Requires-Dist: frozenlist ==1.4.1
Requires-Dist: grpcio ==1.58.0
Requires-Dist: grpcio-tools ==1.58.0
Requires-Dist: h11 ==0.14.0
Requires-Dist: hiredis ==2.3.2
Requires-Dist: httpcore ==1.0.2
Requires-Dist: httpx ==0.27.2
Requires-Dist: idna ==3.6
Requires-Dist: importlib-metadata ==7.0.1
Requires-Dist: itsdangerous ==2.1.2
Requires-Dist: jaraco.classes ==3.3.0
Requires-Dist: Jinja2 ==3.1.3
Requires-Dist: jmespath ==0.10.0
Requires-Dist: keyring ==24.3.0
Requires-Dist: loguru ==0.7.2
Requires-Dist: lxml ==5.1.0
Requires-Dist: markdown-it-py ==3.0.0
Requires-Dist: MarkupSafe ==2.1.5
Requires-Dist: mdurl ==0.1.2
Requires-Dist: more-itertools ==10.2.0
Requires-Dist: multidict ==6.0.5
Requires-Dist: nacos-sdk-python-customer ==0.1.15
Requires-Dist: nh3 ==0.2.15
Requires-Dist: numpy ==1.26.4
Requires-Dist: openpyxl ==3.1.2
Requires-Dist: oss2 ==2.18.4
Requires-Dist: packaging ==24.0
Requires-Dist: pandas ==2.2.0
Requires-Dist: pillow ==10.2.0
Requires-Dist: pkginfo ==1.9.6
Requires-Dist: protobuf ==4.21.6
Requires-Dist: psutil ==5.9.8
Requires-Dist: py ==1.11.0
Requires-Dist: pycparser ==2.21
Requires-Dist: pycryptodome ==3.20.0
Requires-Dist: Pygments ==2.17.2
Requires-Dist: PyMySQL ==1.1.0
Requires-Dist: python-dateutil ==2.8.2
Requires-Dist: python-docx ==1.1.0
Requires-Dist: python-multipart ==0.0.9
Requires-Dist: pytz ==2024.1
Requires-Dist: PyYAML ==6.0.1
Requires-Dist: readme-renderer ==42.0
Requires-Dist: redis ==5.0.1
Requires-Dist: requests ==2.32.3
Requires-Dist: requests-toolbelt ==1.0.0
Requires-Dist: retry ==0.9.2
Requires-Dist: rfc3986 ==2.0.0
Requires-Dist: rich ==13.7.0
Requires-Dist: six ==1.16.0
Requires-Dist: sniffio ==1.3.0
Requires-Dist: SQLAlchemy ==2.0.25
Requires-Dist: starlette ==0.37.2
Requires-Dist: twine ==4.0.2
Requires-Dist: typing-extensions ==4.12.2
Requires-Dist: tzdata ==2023.4
Requires-Dist: tzlocal ==5.2
Requires-Dist: urllib3 ==2.2.0
Requires-Dist: uvicorn ==0.27.0.post1
Requires-Dist: wrapt ==1.16.0
Requires-Dist: yarl ==1.9.4
Requires-Dist: zipp ==3.17.0
